odoo/addons/account_analytic_distribution_manual/README.rst
odoo/addons/account_analytic_distribution_manual/__init__.py
odoo/addons/account_analytic_distribution_manual/__manifest__.py
odoo/addons/account_analytic_distribution_manual/i18n/account_analytic_distribution_manual.pot
odoo/addons/account_analytic_distribution_manual/i18n/ca.po
odoo/addons/account_analytic_distribution_manual/i18n/de.po
odoo/addons/account_analytic_distribution_manual/i18n/es.po
odoo/addons/account_analytic_distribution_manual/i18n/fr.po
odoo/addons/account_analytic_distribution_manual/i18n/it.po
odoo/addons/account_analytic_distribution_manual/i18n/lv.po
odoo/addons/account_analytic_distribution_manual/i18n/sv.po
odoo/addons/account_analytic_distribution_manual/models/__init__.py
odoo/addons/account_analytic_distribution_manual/models/account_analytic_distribution_manual.py
odoo/addons/account_analytic_distribution_manual/models/account_analytic_line.py
odoo/addons/account_analytic_distribution_manual/models/account_move_line.py
odoo/addons/account_analytic_distribution_manual/models/analytic_mixin.py
odoo/addons/account_analytic_distribution_manual/models/base.py
odoo/addons/account_analytic_distribution_manual/readme/CONFIGURE.md
odoo/addons/account_analytic_distribution_manual/readme/CONTRIBUTORS.md
odoo/addons/account_analytic_distribution_manual/readme/DESCRIPTION.md
odoo/addons/account_analytic_distribution_manual/readme/ROADMAP.md
odoo/addons/account_analytic_distribution_manual/readme/USAGE.md
odoo/addons/account_analytic_distribution_manual/reports/__init__.py
odoo/addons/account_analytic_distribution_manual/reports/invoice_report.py
odoo/addons/account_analytic_distribution_manual/security/analytic_security.xml
odoo/addons/account_analytic_distribution_manual/security/ir.model.access.csv
odoo/addons/account_analytic_distribution_manual/static/description/icon.png
odoo/addons/account_analytic_distribution_manual/static/description/index.html
odoo_addon_account_analytic_distribution_manual-18.0.1.0.0.15.dist-info/METADATA
odoo_addon_account_analytic_distribution_manual-18.0.1.0.0.15.dist-info/WHEEL
odoo_addon_account_analytic_distribution_manual-18.0.1.0.0.15.dist-info/top_level.txt
odoo_addon_account_analytic_distribution_manual-18.0.1.0.0.15.dist-info/RECORD
